dnsdb_python_sdk-0.1.2b2.dist-info/DESCRIPTION.rst
dnsdb_python_sdk-0.1.2b2.dist-info/METADATA
dnsdb_python_sdk-0.1.2b2.dist-info/RECORD
dnsdb_python_sdk-0.1.2b2.dist-info/WHEEL
dnsdb_python_sdk-0.1.2b2.dist-info/metadata.json
dnsdb_python_sdk-0.1.2b2.dist-info/top_level.txt
dnsdb_sdk/__init__.py
dnsdb_sdk/api.py
dnsdb_sdk/exceptions.py
